miniworld/__init__.py
miniworld/entity.py
miniworld/math.py
miniworld/miniworld.py
miniworld/objmesh.py
miniworld/opengl.py
miniworld/params.py
miniworld/random.py
miniworld/utils.py
miniworld/wrappers.py
miniworld/envs/__init__.py
miniworld/envs/collecthealth.py
miniworld/envs/fourrooms.py
miniworld/envs/hallway.py
miniworld/envs/maze.py
miniworld/envs/oneroom.py
miniworld/envs/pickupobjs.py
miniworld/envs/putnext.py
miniworld/envs/remotebot.py
miniworld/envs/roomobjs.py
miniworld/envs/sidewalk.py
miniworld/envs/sign.py
miniworld/envs/simtorealgoto.py
miniworld/envs/simtorealpush.py
miniworld/envs/threerooms.py
miniworld/envs/tmaze.py
miniworld/envs/wallgap.py
miniworld/envs/ymaze.py
miniworld-1.0.0.dist-info/LICENSE
miniworld-1.0.0.dist-info/METADATA
miniworld-1.0.0.dist-info/WHEEL
miniworld-1.0.0.dist-info/top_level.txt
miniworld-1.0.0.dist-info/RECORD
