Metadata-Version: 2.1
Name: miniworld
Version: 1.0.0
Author: Farama Foundation
Author-email: jkterry@farama.org
Keywords: environment,agent,rl,gym,robotics,3d
Classifier: Development Status :: 5 - Production/Stable
Classifier: Programming Language :: Python :: 3
Classifier: Programming Language :: Python :: 3.7
Classifier: Programming Language :: Python :: 3.8
Classifier: Programming Language :: Python :: 3.9
Classifier: Programming Language :: Python :: 3.10
Requires-Python: >=3.7, <3.11
License-File: LICENSE
Requires-Dist: gym (>=0.24.0)
Requires-Dist: numpy (>=1.18.0)
Requires-Dist: pyglet (>=1.5.11)
